sva_oauth_client/__init__.py
sva_oauth_client/client.py
sva_oauth_client/decorators.py
sva_oauth_client/middleware.py
sva_oauth_client/urls.py
sva_oauth_client/utils.py
sva_oauth_client/views.py
sva_oauth_client-1.0.1.dist-info/licenses/LICENSE
sva_oauth_client-1.0.1.dist-info/METADATA
sva_oauth_client-1.0.1.dist-info/WHEEL
sva_oauth_client-1.0.1.dist-info/top_level.txt
sva_oauth_client-1.0.1.dist-info/RECORD
