Metadata-Version: 2.4
Name: sva-oauth-client
Version: 1.0.1
Summary: Django package for integrating SVA (Secure Vault Authentication) OAuth provider
Home-page: https://github.com/getsva/sva-oauth-client
Author: SVA Team
Author-email: SVA Team <support@getsva.com>
License: MIT
Keywords: oauth,oauth2,django,sva,authentication,identity
Classifier: Development Status :: 4 - Beta
Classifier: Intended Audience :: Developers
Classifier: License :: OSI Approved :: MIT License
Classifier: Operating System :: OS Independent
Classifier: Programming Language :: Python :: 3
Classifier: Framework :: Django
Requires-Python: >=3.8
License-File: LICENSE
Requires-Dist: Django>=3.2
Requires-Dist: requests>=2.25.0
Requires-Dist: PyJWT>=2.0.0
Provides-Extra: dev
Requires-Dist: pytest>=7.0.0; extra == "dev"
Requires-Dist: pytest-django>=4.5.0; extra == "dev"
Requires-Dist: black>=22.0.0; extra == "dev"
Requires-Dist: flake8>=4.0.0; extra == "dev"
Dynamic: author
Dynamic: home-page
Dynamic: license-file
Dynamic: requires-python
